modbus_sniffer/__init__.py
modbus_sniffer/cli.py
modbus_sniffer/csv_logger.py
modbus_sniffer/gui.py
modbus_sniffer/main_logger.py
modbus_sniffer/modbus_parser_new.py
modbus_sniffer/serial_snooper.py
modbus_sniffer/sniffer_utils.py
modbus_sniffer-1.0.3.dist-info/licenses/LICENSE
modbus_sniffer-1.0.3.dist-info/METADATA
modbus_sniffer-1.0.3.dist-info/WHEEL
modbus_sniffer-1.0.3.dist-info/entry_points.txt
modbus_sniffer-1.0.3.dist-info/top_level.txt
modbus_sniffer-1.0.3.dist-info/RECORD
