Metadata-Version: 2.4
Name: modbus-sniffer
Version: 1.0.3
Summary: Sniffer for Modbus RTU traffic with CLI and GUI
Author-email: niwciu <niwciu@gmail.com>
License-Expression: MIT
License-File: LICENSE
Requires-Dist: pyserial
Requires-Dist: PyQt6
Requires-Dist: rich
Provides-Extra: dev
Requires-Dist: pytest; extra == "dev"
Requires-Dist: pytest-cov; extra == "dev"
Requires-Dist: pytest-qt; extra == "dev"
Requires-Dist: flake8; extra == "dev"
Requires-Dist: black; extra == "dev"
Requires-Dist: pyinstaller; extra == "dev"
Dynamic: license-file
